axtreme/__init__.py
axtreme/evaluation.py
axtreme/experiment.py
axtreme/metrics.py
axtreme/py.typed
axtreme/runner.py
axtreme/acquisition/__init__.py
axtreme/acquisition/qoi_look_ahead.py
axtreme/data/__init__.py
axtreme/data/batch_invariant_sampler.py
axtreme/data/dataset.py
axtreme/data/fixed_random_sample.py
axtreme/data/importance_dataset.py
axtreme/data/multi_dim_batch_sampler.py
axtreme/data/numpy_file_dataset.py
axtreme/data/sizable_sequential_sample.py
axtreme/distributions/__init__.py
axtreme/distributions/helpers.py
axtreme/distributions/icdf.py
axtreme/distributions/mixture.py
axtreme/distributions/utils.py
axtreme/eval/__init__.py
axtreme/eval/object_logging.py
axtreme/eval/qoi_helpers.py
axtreme/eval/qoi_job.py
axtreme/eval/utils.py
axtreme/plotting/__init__.py
axtreme/plotting/doe.py
axtreme/plotting/gp_fit.py
axtreme/plotting/histogram3d.py
axtreme/qoi/__init__.py
axtreme/qoi/gp_bruteforce.py
axtreme/qoi/marginal_cdf_extrapolation.py
axtreme/qoi/qoi_estimator.py
axtreme/sampling/__init__.py
axtreme/sampling/base.py
axtreme/sampling/independent_sampler.py
axtreme/sampling/mean_sampler.py
axtreme/sampling/normal_independent_sampler.py
axtreme/sampling/ut_sampler.py
axtreme/simulator/__init__.py
axtreme/simulator/base.py
axtreme/simulator/utils.py
axtreme/utils/__init__.py
axtreme/utils/distibution_helpers.py
axtreme/utils/experiment_utils.py
axtreme/utils/gradient.py
axtreme/utils/logging.py
axtreme/utils/model_helpers.py
axtreme/utils/modelbridge_utils.py
axtreme/utils/numerical_precision.py
axtreme/utils/population_estimators.py
axtreme/utils/transforms.py
axtreme-0.1.1.dist-info/METADATA
axtreme-0.1.1.dist-info/WHEEL
axtreme-0.1.1.dist-info/licenses/LICENSE
axtreme-0.1.1.dist-info/RECORD
