Metadata-Version: 2.4
Name: axtreme
Version: 0.1.1
Summary: A development library for the RaPiD project
Project-URL: Homepage, https://github.com/dnv-opensource/axtreme
Project-URL: Documentation, https://dnv-opensource.github.io/axtreme/README.html
Project-URL: Repository, https://github.com/dnv-opensource/axtreme.git
Project-URL: Issues, https://github.com/dnv-opensource/axtreme/issues
Project-URL: Changelog, https://github.com/dnv-opensource/axtreme/blob/main/CHANGELOG.md
Author-email: Sebastian Winter <sebastian.winter@dnv.com>, Kristoffer Skare <kristoffer.skare@dnv.com>, Magnus Kristiansen <magnus.kristiansen@dnv.com>
Maintainer-email: Claas Rostock <claas.rostock@dnv.com>, Jorge Luis Mendez <jorge.luis.mendez@dnv.com>
License: MIT License
License-File: LICENSE
Classifier: Development Status :: 3 - Alpha
Classifier: Environment :: Console
Classifier: Intended Audience :: Developers
Classifier: Intended Audience :: Science/Research
Classifier: License :: OSI Approved :: MIT License
Classifier: Operating System :: Microsoft :: Windows
Classifier: Operating System :: POSIX :: Linux
Classifier: Programming Language :: Python :: 3.11
Classifier: Programming Language :: Python :: 3.12
Classifier: Topic :: Scientific/Engineering
Classifier: Topic :: Software Development :: Libraries :: Python Modules
Requires-Python: >=3.11
Requires-Dist: ax-platform[mysql]==0.3.7
Requires-Dist: dataclasses-json>=0.6.7
Requires-Dist: filterpy>=1.4.5
Requires-Dist: gitpython>=3.1.43
Requires-Dist: matplotlib>=3.9
Requires-Dist: numba>=0.60.0
Requires-Dist: numpy<2.0,>=1.26
Requires-Dist: statsmodels>=0.14.4
Provides-Extra: cuda
Requires-Dist: torch==2.4.1+cu124; extra == 'cuda'
